promptlayer/__init__.py
promptlayer/exceptions.py
promptlayer/groups/__init__.py
promptlayer/groups/groups.py
promptlayer/promptlayer.py
promptlayer/promptlayer_base.py
promptlayer/promptlayer_mixins.py
promptlayer/span_exporter.py
promptlayer/streaming/__init__.py
promptlayer/streaming/blueprint_builder.py
promptlayer/streaming/response_handlers.py
promptlayer/streaming/stream_processor.py
promptlayer/templates.py
promptlayer/track/__init__.py
promptlayer/track/track.py
promptlayer/types/__init__.py
promptlayer/types/prompt_template.py
promptlayer/types/request_log.py
promptlayer/utils.py
promptlayer-1.0.82.dist-info/METADATA
promptlayer-1.0.82.dist-info/WHEEL
promptlayer-1.0.82.dist-info/licenses/LICENSE
promptlayer-1.0.82.dist-info/RECORD
