Metadata-Version: 2.4
Name: promptlayer
Version: 1.0.82
Summary: PromptLayer is a platform for prompt engineering and tracks your LLM requests.
License: Apache-2.0
License-File: LICENSE
Author: Magniv
Author-email: hello@magniv.io
Requires-Python: >=3.9,<4.0
Classifier: License :: OSI Approved :: Apache Software License
Classifier: Programming Language :: Python :: 3
Classifier: Programming Language :: Python :: 3.9
Classifier: Programming Language :: Python :: 3.10
Classifier: Programming Language :: Python :: 3.11
Classifier: Programming Language :: Python :: 3.12
Classifier: Programming Language :: Python :: 3.13
Classifier: Programming Language :: Python :: 3.14
Requires-Dist: ably (>=2.0.11,<3.0.0)
Requires-Dist: aiohttp (>=3.10.10,<4.0.0)
Requires-Dist: cachetools (>=5.0.0,<6.0.0)
Requires-Dist: centrifuge-python (>=0.4.1,<0.5.0)
Requires-Dist: httpx (>=0.28.1,<0.29.0)
Requires-Dist: nest-asyncio (>=1.6.0,<2.0.0)
Requires-Dist: opentelemetry-api (>=1.26.0,<2.0.0)
Requires-Dist: opentelemetry-sdk (>=1.26.0,<2.0.0)
Requires-Dist: requests (>=2.31.0,<3.0.0)
Requires-Dist: tenacity (>=9.1.2,<10.0.0)
